django_model_changes/__init__.py
django_model_changes/_version.py
django_model_changes/changes.py
django_model_changes/signals.py
django_model_changes-1.0.3.dist-info/licenses/LICENSE
django_model_changes-1.0.3.dist-info/METADATA
django_model_changes-1.0.3.dist-info/WHEEL
django_model_changes-1.0.3.dist-info/top_level.txt
django_model_changes-1.0.3.dist-info/RECORD
