Metadata-Version: 2.4
Name: django-model-changes
Version: 1.0.3
Summary: Track model instance changes in Django
Author-email: Robert Kajic <robert@kajic.com>
License-Expression: MIT
Project-URL: Homepage, https://github.com/kajic/django-model-changes
Project-URL: Repository, https://github.com/kajic/django-model-changes
Classifier: Environment :: Web Environment
Classifier: Framework :: Django
Classifier: Framework :: Django :: 5.0
Classifier: Framework :: Django :: 5.1
Classifier: Framework :: Django :: 6.0
Classifier: Intended Audience :: Developers
Classifier: Operating System :: OS Independent
Classifier: Programming Language :: Python :: 3
Classifier: Programming Language :: Python :: 3.14
Requires-Python: >=3.14
License-File: LICENSE
Requires-Dist: django<7.0,>=5.0
Dynamic: license-file
